prism/__init__.py
prism/prism.py
prism/tests.py
prism/static/codemirror/codemirror.css
prism/static/codemirror/codemirror.js
prism/static/css/dark.css
prism/static/css/light.css
prism/static/css/prism.css
prism/static/html/lms.html
prism/static/html/studio.html
prism/static/js/src/prism.js
prism/static/js/src/studio.js
xblock_prismjs-0.1.4.dist-info/LICENSE
xblock_prismjs-0.1.4.dist-info/METADATA
xblock_prismjs-0.1.4.dist-info/WHEEL
xblock_prismjs-0.1.4.dist-info/entry_points.txt
xblock_prismjs-0.1.4.dist-info/top_level.txt
xblock_prismjs-0.1.4.dist-info/RECORD
