Metadata-Version: 2.1
Name: xblock-prismjs
Version: 0.1.4
Summary: Open EdX XBlock for syntax highlight via Prism JS
Home-page: UNKNOWN
Author: Esther Suh, Appsembler
License: UNKNOWN
Platform: UNKNOWN
License-File: LICENSE
Requires-Dist: XBlock
